CHANGES.md
CLASSIFIERS.txt
LICENSE.md
MANIFEST.in
README.md
ez_setup.py
requirements.txt
setup.py
django_drift.egg-info/PKG-INFO
django_drift.egg-info/SOURCES.txt
django_drift.egg-info/dependency_links.txt
django_drift.egg-info/requires.txt
django_drift.egg-info/top_level.txt
drift/__init__.py
drift/admin.py
drift/forms.py
drift/importers.py
drift/loaders.py
drift/models.py
drift/signals.py
drift/tasks.py
drift/views.py
drift/management/__init__.py
drift/management/commands/__init__.py
drift/management/commands/drift.py
drift/templates/drift/import.html