Metadata-Version: 1.0
Name: django-drift
Version: 0.1.2
Summary: Takes files and turns them into recrods in models. HOORAY!
Home-page: http://github.com/monokrome/django-drift
Author: Brandon R. Stoner
Author-email: monokrome@limpidtech.com
License: UNKNOWN
Platform: UNKNOWN
